xlmhg/__init__.py
xlmhg/mhg.py
xlmhg/mhg_cython.cpython-35m-darwin.so
xlmhg/result.py
xlmhg/test.py
xlmhg/visualize.py
xlmhg-2.5.4.dist-info/METADATA
xlmhg-2.5.4.dist-info/RECORD
xlmhg-2.5.4.dist-info/WHEEL
xlmhg-2.5.4.dist-info/top_level.txt
