Metadata-Version: 2.1
Name: xlmhg
Version: 2.5.4
Summary: XL-mHG: A Semiparametric Test for Enrichment
Home-page: https://github.com/flo-compbio/xlmhg
Author: Florian Wagner
Author-email: florian.wagner@duke.edu
License: GPLv3
Keywords: statistics nonparametric semiparametric enrichment test ranked lists
Platform: UNKNOWN
Classifier: Development Status :: 4 - Beta
Classifier: Intended Audience :: Developers
Classifier: Intended Audience :: Science/Research
Classifier: Topic :: Scientific/Engineering :: Bio-Informatics
Classifier: License :: OSI Approved :: BSD License
Classifier: Programming Language :: Python :: 3.5
Classifier: Programming Language :: Python :: 3.6
Classifier: Programming Language :: Python :: 3.7
Classifier: Programming Language :: Python :: 3.8
Classifier: Programming Language :: Cython
Provides-Extra: tests
Provides-Extra: docs
Requires-Dist: plotly (>=3)
Requires-Dist: pip (>=19)
Requires-Dist: cython (<1,>=0.25)
Requires-Dist: numpy (<2,>=1.15)
Provides-Extra: docs
Requires-Dist: sphinx (<2,>=1.4.5); extra == 'docs'
Requires-Dist: sphinx-rtd-theme (>=0.1.9); extra == 'docs'
Requires-Dist: sphinxcontrib-napoleon (>=0.5.3); extra == 'docs'
Provides-Extra: tests
Requires-Dist: pytest (<6,>=2.8.5); extra == 'tests'
Requires-Dist: pytest-cov (<3,>=2.2.1); extra == 'tests'
Requires-Dist: scipy (<2,>=1.1); extra == 'tests'
